CHANGES.txt
LICENSE.txt
MANIFEST.in
README.md
setup.py
rekey/__init__.py
rekey/native.py
rekey/rekey.py
rekey/rekeyable.py
rekey.egg-info/PKG-INFO
rekey.egg-info/SOURCES.txt
rekey.egg-info/dependency_links.txt
rekey.egg-info/requires.txt
rekey.egg-info/top_level.txt