Metadata-Version: 1.1
Name: rekey
Version: 1.2.0
Summary: enumerable utility
Home-page: https://github.com/dpep/pyrekey
Author: Daniel Pepper
Author-email: UNKNOWN
License: MIT
Platform: any
Classifier: License :: OSI Approved :: MIT License
Classifier: Natural Language :: English
Classifier: Operating System :: OS Independent
Classifier: Topic :: Utilities
